QuantGaussBinomial/Binomialdistribution.py
QuantGaussBinomial/Gaussiandistribution.py
QuantGaussBinomial/Generaldistribution.py
QuantGaussBinomial/__init__.py
QuantGaussBinomial-1.9.dist-info/LICENSE.md
QuantGaussBinomial-1.9.dist-info/METADATA
QuantGaussBinomial-1.9.dist-info/WHEEL
QuantGaussBinomial-1.9.dist-info/top_level.txt
QuantGaussBinomial-1.9.dist-info/RECORD
