Metadata-Version: 2.1
Name: QuantGaussBinomial
Version: 1.9
Summary: A Python package for easy manipulation and calculation with Gaussian and Binomial distributions.
Home-page: https://github.com/RichieSater/QuantGaussBinomial
Author: Richie Sater
Author-email: RichieSater@gmail.com
License: MIT
Keywords: gaussian binomial distributions statistics
Classifier: Development Status :: 3 - Alpha
Classifier: Intended Audience :: Education
Classifier: Intended Audience :: Science/Research
Classifier: License :: OSI Approved :: MIT License
Classifier: Programming Language :: Python :: 3
Classifier: Programming Language :: Python :: 3.8
Classifier: Topic :: Scientific/Engineering :: Mathematics
License-File: LICENSE.md
